.gitignore
.pre-commit-config.yaml
.pylintrc
.readthedocs.yaml
CODE_OF_CONDUCT.md
LICENSE
README.rst
README.rst.license
pyproject.toml
requirements.txt
setup.py
sparkfun_qwiicrelay.py
.github/PULL_REQUEST_TEMPLATE/adafruit_circuitpython_pr.md
.github/workflows/build.yml
.github/workflows/failure-help-text.yml
.github/workflows/release.yml
LICENSES/CC-BY-4.0.txt
LICENSES/MIT.txt
LICENSES/Unlicense.txt
docs/api.rst
docs/api.rst.license
docs/conf.py
docs/examples.rst
docs/examples.rst.license
docs/index.rst
docs/index.rst.license
docs/requirements.txt
docs/_static/favicon.ico
docs/_static/favicon.ico.license
examples/example1_basic_control.py
examples/example2_change_i2c_address.py
examples/example3_i2c_scanner.py
examples/example4_get_relay_status.py
examples/example5_get_firmware_version.py
examples/example6_set_relay_status.py
examples/qwiicrelay_simpletest.py
sparkfun_circuitpython_qwiicrelay.egg-info/PKG-INFO
sparkfun_circuitpython_qwiicrelay.egg-info/SOURCES.txt
sparkfun_circuitpython_qwiicrelay.egg-info/dependency_links.txt
sparkfun_circuitpython_qwiicrelay.egg-info/requires.txt
sparkfun_circuitpython_qwiicrelay.egg-info/top_level.txt